{"problems": [{"name": "Information Disturbing", "link": "/problem/12314/origin"}, {"name": "B-number", "link": "/problem/12990/origin"}, {"name": "Successor", "link": "/problem/31145/origin"}, {"name": "Muddy Fields", "link": "/problem/16512/origin"}, {"name": "One Unit Machine", "link": "/problem/26937/origin"}, {"name": "Data Handler", "link": "/problem/31868/origin"}, {"name": "Bankrupt Baker", "link": "/problem/35142/origin"}, {"name": "Devices", "link": "/problem/61984/origin"}, {"name": "Roads not only in Berland", "link": "/problem/20796/origin"}, {"name": "Eternal Victory", "link": "/problem/21375/origin"}], "participants": [{"rank": 1, "name": "draak_krijger ", "href": "/user/draak_krijger", "type": "previous", "score": 4, "penalty": 2382}, {"rank": 2, "name": "dot0 ", "href": "/user/dot0", "type": "previous", "score": 4, "penalty": 4068}, {"rank": 3, "name": "sojiro_seta ", "href": "/user/sojiro_seta", "type": "previous", "score": 4, "penalty": 4098}, {"rank": 4, "name": "define_SUST ", "href": "/user/define_SUST", "type": "previous", "score": 3, "penalty": 824}, {"rank": 5, "name": "meem_sust", "href": "/user/meem_sust", "type": "current", "score": 3, "penalty": 2469}, {"rank": 6, "name": "Mahir_sust ", "href": "/user/Mahir_sust", "type": "previous", "score": 3, "penalty": 2844}, {"rank": 7, "name": "Jakir_sust ", "href": "/user/Jakir_sust", "type": "previous", "score": 2, "penalty": 196}, {"rank": 8, "name": "shapath ", "href": "/user/shapath", "type": "previous", "score": 1, "penalty": 41}, {"rank": 9, "name": "shahriar_sust13 ", "href": "/user/shahriar_sust13", "type": "previous", "score": 1, "penalty": 80}, {"rank": 10, "name": "2013331036", "href": "/user/2013331036", "type": "current", "score": 1, "penalty": 91}, {"rank": 11, "name": "kashem__SUST ", "href": "/user/kashem__SUST", "type": "previous", "score": 0, "penalty": 0}, {"rank": 12, "name": "NinjaNineteen ", "href": "/user/NinjaNineteen", "type": "previous", "score": 0, "penalty": 0}]}