{"problems": [{"name": "Exponentiation", "link": "/problem/16133/origin"}], "participants": [{"rank": 1, "name": "paopao123", "href": "/user/paopao123", "type": "current", "score": 1, "penalty": 0}, {"rank": 2, "name": "NUC_shike ", "href": "/user/NUC_shike", "type": "previous", "score": 1, "penalty": 1}, {"rank": 3, "name": "NUC_WangZhiqiang ", "href": "/user/NUC_WangZhiqiang", "type": "previous", "score": 1, "penalty": 33}, {"rank": 4, "name": "tjndsg ", "href": "/user/tjndsg", "type": "previous", "score": 1, "penalty": 44}, {"rank": 5, "name": "bezorro ", "href": "/user/bezorro", "type": "previous", "score": 1, "penalty": 65}, {"rank": 6, "name": "nka_kun ", "href": "/user/nka_kun", "type": "previous", "score": 1, "penalty": 69}, {"rank": 7, "name": "yzm10 ", "href": "/user/yzm10", "type": "previous", "score": 1, "penalty": 69}, {"rank": 8, "name": "TestAve ", "href": "/user/TestAve", "type": "previous", "score": 1, "penalty": 71}, {"rank": 9, "name": "fyyy1992", "href": "/user/fyyy1992", "type": "current", "score": 1, "penalty": 89}, {"rank": 10, "name": "sanae", "href": "/user/sanae", "type": "current", "score": 0, "penalty": 0}, {"rank": 11, "name": "bjtu_ac_monster", "href": "/user/bjtu_ac_monster", "type": "current", "score": 0, "penalty": 0}, {"rank": 12, "name": "HDU_ACE ", "href": "/user/HDU_ACE", "type": "previous", "score": 0, "penalty": 0}, {"rank": 13, "name": "qqname ", "href": "/user/qqname", "type": "previous", "score": 0, "penalty": 0}, {"rank": 14, "name": "1302130222 ", "href": "/user/1302130222", "type": "previous", "score": 0, "penalty": 0}, {"rank": 15, "name": "16110501008 ", "href": "/user/16110501008", "type": "previous", "score": 0, "penalty": 0}, {"rank": 16, "name": "18805928160", "href": "/user/18805928160", "type": "current", "score": 0, "penalty": 0}, {"rank": 17, "name": "MinecraftFuns ", "href": "/user/MinecraftFuns", "type": "previous", "score": 0, "penalty": 0}, {"rank": 18, "name": "chen_lijie ", "href": "/user/chen_lijie", "type": "previous", "score": 0, "penalty": 0}, {"rank": 19, "name": "ascteam ", "href": "/user/ascteam", "type": "previous", "score": 0, "penalty": 0}]}