{"problems": [{"name": "Average Convex Hull", "link": "/problem/198747/origin"}, {"name": "Binary Suffix Array", "link": "/problem/198751/origin"}, {"name": "Collision Detection", "link": "/problem/198753/origin"}, {"name": "Dual Cure", "link": "/problem/198754/origin"}, {"name": "Elections", "link": "/problem/198755/origin"}, {"name": "Free of Squares", "link": "/problem/198756/origin"}, {"name": "Gas Transportation", "link": "/problem/198757/origin"}, {"name": "Handsome Division", "link": "/problem/198759/origin"}, {"name": "In Touch", "link": "/problem/198760/origin"}, {"name": "Jumbo World", "link": "/problem/198761/origin"}], "participants": [{"rank": 1, "name": "murasame ", "href": "/user/murasame", "type": "previous", "score": 6, "penalty": 645}, {"rank": 2, "name": "Piculus", "href": "/user/Piculus", "type": "current", "score": 6, "penalty": 889}, {"rank": 3, "name": "Zugspitze", "href": "/user/Zugspitze", "type": "current", "score": 6, "penalty": 923}, {"rank": 4, "name": "Rayo ", "href": "/user/Rayo", "type": "previous", "score": 6, "penalty": 1043}, {"rank": 5, "name": "Immanuel ", "href": "/user/Immanuel", "type": "previous", "score": 5, "penalty": 472}, {"rank": 6, "name": "this_is_a_team ", "href": "/user/this_is_a_team", "type": "previous", "score": 5, "penalty": 774}, {"rank": 7, "name": "Antonidas", "href": "/user/Antonidas", "type": "current", "score": 5, "penalty": 904}, {"rank": 8, "name": "SUST_TeamX ", "href": "/user/SUST_TeamX", "type": "previous", "score": 4, "penalty": 498}, {"rank": 9, "name": "teamQI ", "href": "/user/teamQI", "type": "previous", "score": 4, "penalty": 690}, {"rank": 10, "name": "uestc_poi", "href": "/user/uestc_poi", "type": "current", "score": 4, "penalty": 746}, {"rank": 11, "name": "BlackHot ", "href": "/user/BlackHot", "type": "previous", "score": 3, "penalty": 509}, {"rank": 12, "name": "du_gian", "href": "/user/du_gian", "type": "current", "score": 3, "penalty": 603}, {"rank": 13, "name": "UESTC_Jirachi ", "href": "/user/UESTC_Jirachi", "type": "previous", "score": 3, "penalty": 674}, {"rank": 14, "name": "hiyot", "href": "/user/hiyot", "type": "current", "score": 3, "penalty": 697}, {"rank": 15, "name": "sazerterus ", "href": "/user/sazerterus", "type": "previous", "score": 3, "penalty": 710}, {"rank": 16, "name": "Censored_by_3", "href": "/user/Censored_by_3", "type": "current", "score": 2, "penalty": 277}, {"rank": 17, "name": "JU_Circavex ", "href": "/user/JU_Circavex", "type": "previous", "score": 2, "penalty": 345}, {"rank": 18, "name": "DragonSlayer", "href": "/user/DragonSlayer", "type": "current", "score": 1, "penalty": 77}, {"rank": 19, "name": "UESTC_2NIW3IJLCL", "href": "/user/UESTC_2NIW3IJLCL", "type": "current", "score": 1, "penalty": 89}, {"rank": 20, "name": "2013551629 ", "href": "/user/2013551629", "type": "previous", "score": 1, "penalty": 139}, {"rank": 21, "name": "Buet_Negasimyy ", "href": "/user/Buet_Negasimyy", "type": "previous", "score": 1, "penalty": 313}, {"rank": 22, "name": "mahbubcseju ", "href": "/user/mahbubcseju", "type": "previous", "score": 0, "penalty": 0}, {"rank": 23, "name": "1205028 ", "href": "/user/1205028", "type": "previous", "score": 0, "penalty": 0}]}