{"problems": [{"name": "Load Balancing", "link": "/problem/96766/origin"}, {"name": "Jersey Number", "link": "/problem/102737/origin"}, {"name": "Numbered Cards", "link": "/problem/292535/origin"}, {"name": "String Theory", "link": "/problem/498326/origin"}, {"name": "Food Delivery", "link": "/problem/17141/origin"}, {"name": "Flyovers of Khakha", "link": "/problem/206468/origin"}, {"name": "The Values You Can Make", "link": "/problem/407724/origin"}, {"name": "Alyona and Strings", "link": "/problem/403363/origin"}, {"name": "Increasing Xor Sequence", "link": "/problem/767350/origin"}, {"name": "Bear and Bowling 4", "link": "/problem/359889/origin"}, {"name": "Digit Count", "link": "/problem/26836/origin"}, {"name": "Product Sum", "link": "/problem/333889/origin"}], "participants": [{"rank": 1, "name": "sjshohag ", "href": "/user/sjshohag", "type": "previous", "score": 6, "penalty": 5945}, {"rank": 2, "name": "PP_Paul ", "href": "/user/PP_Paul", "type": "previous", "score": 6, "penalty": 9725}, {"rank": 3, "name": "PP_Paul ", "href": "/user/PP_Paul", "type": "previous", "score": 4, "penalty": 4004}, {"rank": 4, "name": "Avik_2016331009 ", "href": "/user/Avik_2016331009", "type": "previous", "score": 4, "penalty": 5040}, {"rank": 5, "name": "Shahidul1004 ", "href": "/user/Shahidul1004", "type": "previous", "score": 4, "penalty": 9805}, {"rank": 6, "name": "foysal87 ", "href": "/user/foysal87", "type": "previous", "score": 4, "penalty": 11182}, {"rank": 7, "name": "Tanvir_Hossain ", "href": "/user/Tanvir_Hossain", "type": "previous", "score": 3, "penalty": 7037}, {"rank": 8, "name": "Shahriar_Habib ", "href": "/user/Shahriar_Habib", "type": "previous", "score": 3, "penalty": 17804}, {"rank": 9, "name": "ettehadul ", "href": "/user/ettehadul", "type": "previous", "score": 3, "penalty": 24540}, {"rank": 10, "name": "sdipto ", "href": "/user/sdipto", "type": "previous", "score": 2, "penalty": 2223}, {"rank": 11, "name": "Arnobkumarsaha ", "href": "/user/Arnobkumarsaha", "type": "previous", "score": 2, "penalty": 2539}, {"rank": 12, "name": "sdipto ", "href": "/user/sdipto", "type": "previous", "score": 2, "penalty": 3386}, {"rank": 13, "name": "Faiyaz_Khan ", "href": "/user/Faiyaz_Khan", "type": "previous", "score": 2, "penalty": 5113}, {"rank": 14, "name": "Shahidul1004 ", "href": "/user/Shahidul1004", "type": "previous", "score": 2, "penalty": 6102}, {"rank": 15, "name": "TasdidurRahman ", "href": "/user/TasdidurRahman", "type": "previous", "score": 2, "penalty": 8819}, {"rank": 16, "name": "BIJOY_SUST ", "href": "/user/BIJOY_SUST", "type": "previous", "score": 2, "penalty": 8907}, {"rank": 17, "name": "ayon2016331096 ", "href": "/user/ayon2016331096", "type": "previous", "score": 2, "penalty": 9118}, {"rank": 18, "name": "Faiyaz_Khan ", "href": "/user/Faiyaz_Khan", "type": "previous", "score": 2, "penalty": 9872}, {"rank": 19, "name": "Arup_Datta ", "href": "/user/Arup_Datta", "type": "previous", "score": 2, "penalty": 10843}, {"rank": 20, "name": "TasdidurRahman ", "href": "/user/TasdidurRahman", "type": "previous", "score": 2, "penalty": 14558}, {"rank": 21, "name": "phoenix06 ", "href": "/user/phoenix06", "type": "previous", "score": 2, "penalty": 17456}, {"rank": 22, "name": "pavel2016331046 ", "href": "/user/pavel2016331046", "type": "previous", "score": 1, "penalty": 820}, {"rank": 23, "name": "Linkon45 ", "href": "/user/Linkon45", "type": "previous", "score": 1, "penalty": 2079}, {"rank": 24, "name": "Nirzak ", "href": "/user/Nirzak", "type": "previous", "score": 1, "penalty": 4608}, {"rank": 25, "name": "phoenix06 ", "href": "/user/phoenix06", "type": "previous", "score": 1, "penalty": 5572}, {"rank": 26, "name": "SUST_cosmos ", "href": "/user/SUST_cosmos", "type": "previous", "score": 1, "penalty": 5590}, {"rank": 27, "name": "ettehadul ", "href": "/user/ettehadul", "type": "previous", "score": 1, "penalty": 6181}, {"rank": 28, "name": "Mahir101 ", "href": "/user/Mahir101", "type": "previous", "score": 1, "penalty": 6908}, {"rank": 29, "name": "Mahir101 ", "href": "/user/Mahir101", "type": "previous", "score": 1, "penalty": 7322}, {"rank": 30, "name": "Avik_2016331009 ", "href": "/user/Avik_2016331009", "type": "previous", "score": 1, "penalty": 7392}, {"rank": 31, "name": "rifa ", "href": "/user/rifa", "type": "previous", "score": 1, "penalty": 8839}, {"rank": 32, "name": "istiakpappu ", "href": "/user/istiakpappu", "type": "previous", "score": 1, "penalty": 8971}, {"rank": 33, "name": "rifa ", "href": "/user/rifa", "type": "previous", "score": 0, "penalty": 0}, {"rank": 34, "name": "pavel2016331046 ", "href": "/user/pavel2016331046", "type": "previous", "score": 0, "penalty": 0}]}