{"problems": [{"name": "Limited Permutation", "link": "/problem/938259/origin"}, {"name": "Problem A. Ascending Rating", "link": "/problem/1734323/origin"}, {"name": "Ocean Deep! - Make it shallow!!", "link": "/problem/19954/origin"}, {"name": "Problem F. Grab The Tree", "link": "/problem/1734354/origin"}, {"name": "Problem M. Walking Plan", "link": "/problem/1734364/origin"}, {"name": "I am Dumb 3", "link": "/problem/32717/origin"}], "participants": [{"rank": 1, "name": "Jubair_Araf ", "href": "/user/Jubair_Araf", "type": "previous", "score": 3, "penalty": 192}, {"rank": 2, "name": "sjshohag ", "href": "/user/sjshohag", "type": "previous", "score": 3, "penalty": 268}, {"rank": 3, "name": "Avik_2016331009 ", "href": "/user/Avik_2016331009", "type": "previous", "score": 3, "penalty": 392}, {"rank": 4, "name": "John_Constantine ", "href": "/user/John_Constantine", "type": "previous", "score": 3, "penalty": 491}, {"rank": 5, "name": "arnab1_0_1 ", "href": "/user/arnab1_0_1", "type": "previous", "score": 3, "penalty": 531}, {"rank": 6, "name": "Avi2015331026 ", "href": "/user/Avi2015331026", "type": "previous", "score": 2, "penalty": 83}, {"rank": 7, "name": "steinum ", "href": "/user/steinum", "type": "previous", "score": 2, "penalty": 96}, {"rank": 8, "name": "Shahidul1004 ", "href": "/user/Shahidul1004", "type": "previous", "score": 2, "penalty": 106}, {"rank": 9, "name": "Shahriar_Habib ", "href": "/user/Shahriar_Habib", "type": "previous", "score": 2, "penalty": 142}, {"rank": 10, "name": "2017331063 ", "href": "/user/2017331063", "type": "previous", "score": 2, "penalty": 166}, {"rank": 11, "name": "Tahseen ", "href": "/user/Tahseen", "type": "previous", "score": 2, "penalty": 225}, {"rank": 12, "name": "2017331064 ", "href": "/user/2017331064", "type": "previous", "score": 2, "penalty": 262}, {"rank": 13, "name": "2017331047 ", "href": "/user/2017331047", "type": "previous", "score": 1, "penalty": 28}, {"rank": 14, "name": "aritra741 ", "href": "/user/aritra741", "type": "previous", "score": 1, "penalty": 58}, {"rank": 15, "name": "BIJOY_SUST ", "href": "/user/BIJOY_SUST", "type": "previous", "score": 1, "penalty": 65}, {"rank": 16, "name": "2017331095 ", "href": "/user/2017331095", "type": "previous", "score": 1, "penalty": 71}, {"rank": 17, "name": "mish13 ", "href": "/user/mish13", "type": "previous", "score": 1, "penalty": 75}, {"rank": 18, "name": "NirobSUST ", "href": "/user/NirobSUST", "type": "previous", "score": 1, "penalty": 96}, {"rank": 19, "name": "2017331025 ", "href": "/user/2017331025", "type": "previous", "score": 1, "penalty": 96}, {"rank": 20, "name": "A_T ", "href": "/user/A_T", "type": "previous", "score": 1, "penalty": 100}, {"rank": 21, "name": "RakibulRanak ", "href": "/user/RakibulRanak", "type": "previous", "score": 1, "penalty": 102}, {"rank": 22, "name": "2017331006 ", "href": "/user/2017331006", "type": "previous", "score": 1, "penalty": 108}, {"rank": 23, "name": "2017331068 ", "href": "/user/2017331068", "type": "previous", "score": 1, "penalty": 143}, {"rank": 24, "name": "Henrick993 ", "href": "/user/Henrick993", "type": "previous", "score": 1, "penalty": 164}, {"rank": 25, "name": "2017331059 ", "href": "/user/2017331059", "type": "previous", "score": 1, "penalty": 204}, {"rank": 26, "name": "prishan076 ", "href": "/user/prishan076", "type": "previous", "score": 0, "penalty": 0}, {"rank": 27, "name": "2018331081 ", "href": "/user/2018331081", "type": "previous", "score": 0, "penalty": 0}, {"rank": 28, "name": "2018331119 ", "href": "/user/2018331119", "type": "previous", "score": 0, "penalty": 0}]}